donkey/__init__.py
donkey/cli.py
donkey/logs.py
donkey/main.py
donkey/version.py
donkey_make-0.0.4.dist-info/DESCRIPTION.rst
donkey_make-0.0.4.dist-info/METADATA
donkey_make-0.0.4.dist-info/RECORD
donkey_make-0.0.4.dist-info/WHEEL
donkey_make-0.0.4.dist-info/entry_points.txt
donkey_make-0.0.4.dist-info/metadata.json
donkey_make-0.0.4.dist-info/top_level.txt
donkey_make-0.0.4.dist-info/zip-safe
