Metadata-Version: 2.0
Name: donkey-make
Version: 0.0.4
Summary: Like make but for the 21st century.
Home-page: https://github.com/samuelcolvin/donkey
Author: Samuel Colvin
Author-email: s@muelcolvin.com
License: MIT
Platform: UNKNOWN
Classifier: Development Status :: 3 - Alpha
Classifier: Environment :: Console
Classifier: Programming Language :: Python
Classifier: Programming Language :: Python :: 3
Classifier: Programming Language :: Python :: 3.5
Classifier: Intended Audience :: Developers
Classifier: Intended Audience :: Information Technology
Classifier: Intended Audience :: System Administrators
Classifier: License :: OSI Approved :: MIT License
Classifier: Operating System :: Unix
Classifier: Operating System :: POSIX :: Linux
Classifier: Topic :: Software Development :: Libraries :: Python Modules
Classifier: Topic :: System :: Systems Administration
Requires-Dist: PyYAML (>=3.12)
Requires-Dist: click (>=6.6)
Requires-Dist: trafaret (>=0.7.5)
Requires-Dist: trafaret-config (>=0.1.1)
Requires-Dist: watchdog (>=0.8.3)
